sml_exporter/__init__.py
sml_exporter/__main__.py
sml_exporter-0.1.5.dist-info/LICENSE
sml_exporter-0.1.5.dist-info/METADATA
sml_exporter-0.1.5.dist-info/WHEEL
sml_exporter-0.1.5.dist-info/entry_points.txt
sml_exporter-0.1.5.dist-info/RECORD
