Metadata-Version: 2.1
Name: sml-exporter
Version: 0.1.5
Summary: Smartmeter Message Language Prometheus Exporter
Home-page: https://github.com/mweinelt/sml-exporter
License: MIT
Keywords: smartmeter,prometheus,exporter
Author: Martin Weinelt
Author-email: hexa@darmstadt.ccc.de
Requires-Python: >=3.8,<4.0
Classifier: License :: OSI Approved :: MIT License
Classifier: Programming Language :: Python :: 3
Classifier: Programming Language :: Python :: 3.8
Classifier: Programming Language :: Python :: 3.9
Classifier: Programming Language :: Python :: 3.10
Classifier: Programming Language :: Python :: 3.11
Classifier: Programming Language :: Python :: 3.10
Classifier: Programming Language :: Python :: 3.11
Classifier: Programming Language :: Python :: 3.8
Classifier: Programming Language :: Python :: 3.9
Requires-Dist: click (>=8,<9)
Requires-Dist: prometheus-client (>=0,<1)
Requires-Dist: pysml (==0.0.11)
Project-URL: Repository, https://github.com/mweinelt/sml-exporter
